{
    "problem_title": "Day",
    "text_input": "Day{problem_no:02d}_input",
    "challenge_id": "AOC_2023",
    "challenge_folder": "2023",
    "problem_folder": "{problem_no:02d}",
    "solution_file": "2023Day{problem_no:02d}.{lang}",
    "challenge_header": "Advent of Codes: Year 2023(Snow Crisis)!",
    "plot_color": "#23C3A0",
    "script_header": "Advent of Code - Day {problem_no}, Year 2023\nSolution Started: {month} {current_time.tm_mday}, {current_time.tm_year}\nPuzzle Link: https://adventofcode.com/2023/day/{problem_no}\nSolution by: {author}\nBrief: [Code/Problem Description]"
}